acciodata/__init__.py
acciodata-0.0.1.dist-info/licenses/LICENSE
acciodata-0.0.1.dist-info/METADATA
acciodata-0.0.1.dist-info/WHEEL
acciodata-0.0.1.dist-info/top_level.txt
acciodata-0.0.1.dist-info/RECORD
